{
  "id": "52a2ac75-6fb7-4a7d-83b7-ae1b80a7ad46",
  "prevId": "00000000-0000-0000-0000-000000000000",
  "version": "7",
  "dialect": "postgresql",
  "tables": {
    "public.ai_jobs": {
      "name": "ai_jobs",
      "schema": "",
      "columns": {
        "id": {
          "name": "id",
          "type": "varchar",
          "primaryKey": true,
          "notNull": true
        },
        "user_id": {
          "name": "user_id",
          "type": "varchar",
          "primaryKey": false,
          "notNull": true
        },
        "shoot_id": {
          "name": "shoot_id",
          "type": "varchar",
          "primaryKey": false,
          "notNull": true
        },
        "tool": {
          "name": "tool",
          "type": "varchar(50)",
          "primaryKey": false,
          "notNull": true
        },
        "model_slug": {
          "name": "model_slug",
          "type": "varchar(100)",
          "primaryKey": false,
          "notNull": true
        },
        "source_image_key": {
          "name": "source_image_key",
          "type": "text",
          "primaryKey": false,
          "notNull": true
        },
        "output_image_key": {
          "name": "output_image_key",
          "type": "text",
          "primaryKey": false,
          "notNull": false
        },
        "params": {
          "name": "params",
          "type": "text",
          "primaryKey": false,
          "notNull": false
        },
        "external_job_id": {
          "name": "external_job_id",
          "type": "text",
          "primaryKey": false,
          "notNull": false
        },
        "status": {
          "name": "status",
          "type": "varchar(20)",
          "primaryKey": false,
          "notNull": true,
          "default": "'pending'"
        },
        "cost": {
          "name": "cost",
          "type": "bigint",
          "primaryKey": false,
          "notNull": false
        },
        "credits": {
          "name": "credits",
          "type": "bigint",
          "primaryKey": false,
          "notNull": false
        },
        "error_message": {
          "name": "error_message",
          "type": "text",
          "primaryKey": false,
          "notNull": false
        },
        "webhook_received_at": {
          "name": "webhook_received_at",
          "type": "bigint",
          "primaryKey": false,
          "notNull": false
        },
        "completed_at": {
          "name": "completed_at",
          "type": "bigint",
          "primaryKey": false,
          "notNull": false
        },
        "created_at": {
          "name": "created_at",
          "type": "bigint",
          "primaryKey": false,
          "notNull": true
        }
      },
      "indexes": {},
      "foreignKeys": {
        "ai_jobs_user_id_users_id_fk": {
          "name": "ai_jobs_user_id_users_id_fk",
          "tableFrom": "ai_jobs",
          "tableTo": "users",
          "columnsFrom": [
            "user_id"
          ],
          "columnsTo": [
            "id"
          ],
          "onDelete": "cascade",
          "onUpdate": "no action"
        },
        "ai_jobs_shoot_id_shoots_id_fk": {
          "name": "ai_jobs_shoot_id_shoots_id_fk",
          "tableFrom": "ai_jobs",
          "tableTo": "shoots",
          "columnsFrom": [
            "shoot_id"
          ],
          "columnsTo": [
            "id"
          ],
          "onDelete": "cascade",
          "onUpdate": "no action"
        }
      },
      "compositePrimaryKeys": {},
      "uniqueConstraints": {},
      "policies": {},
      "checkConstraints": {},
      "isRLSEnabled": false
    },
    "public.booking_items": {
      "name": "booking_items",
      "schema": "",
      "columns": {
        "id": {
          "name": "id",
          "type": "varchar",
          "primaryKey": true,
          "notNull": true
        },
        "booking_id": {
          "name": "booking_id",
          "type": "varchar",
          "primaryKey": false,
          "notNull": true
        },
        "service_id": {
          "name": "service_id",
          "type": "varchar",
          "primaryKey": false,
          "notNull": true
        },
        "quantity": {
          "name": "quantity",
          "type": "bigint",
          "primaryKey": false,
          "notNull": true,
          "default": 1
        },
        "unit_price": {
          "name": "unit_price",
          "type": "bigint",
          "primaryKey": false,
          "notNull": true
        },
        "total_price": {
          "name": "total_price",
          "type": "bigint",
          "primaryKey": false,
          "notNull": true
        },
        "created_at": {
          "name": "created_at",
          "type": "bigint",
          "primaryKey": false,
          "notNull": true
        }
      },
      "indexes": {},
      "foreignKeys": {
        "booking_items_booking_id_bookings_id_fk": {
          "name": "booking_items_booking_id_bookings_id_fk",
          "tableFrom": "booking_items",
          "tableTo": "bookings",
          "columnsFrom": [
            "booking_id"
          ],
          "columnsTo": [
            "id"
          ],
          "onDelete": "cascade",
          "onUpdate": "no action"
        },
        "booking_items_service_id_services_id_fk": {
          "name": "booking_items_service_id_services_id_fk",
          "tableFrom": "booking_items",
          "tableTo": "services",
          "columnsFrom": [
            "service_id"
          ],
          "columnsTo": [
            "id"
          ],
          "onDelete": "restrict",
          "onUpdate": "no action"
        }
      },
      "compositePrimaryKeys": {},
      "uniqueConstraints": {},
      "policies": {},
      "checkConstraints": {},
      "isRLSEnabled": false
    },
    "public.bookings": {
      "name": "bookings",
      "schema": "",
      "columns": {
        "id": {
          "name": "id",
          "type": "varchar",
          "primaryKey": true,
          "notNull": true
        },
        "user_id": {
          "name": "user_id",
          "type": "varchar",
          "primaryKey": false,
          "notNull": true
        },
        "region": {
          "name": "region",
          "type": "varchar(3)",
          "primaryKey": false,
          "notNull": true
        },
        "kilometers": {
          "name": "kilometers",
          "type": "bigint",
          "primaryKey": false,
          "notNull": false
        },
        "contact_name": {
          "name": "contact_name",
          "type": "varchar(255)",
          "primaryKey": false,
          "notNull": false
        },
        "contact_email": {
          "name": "contact_email",
          "type": "varchar(255)",
          "primaryKey": false,
          "notNull": false
        },
        "contact_mobile": {
          "name": "contact_mobile",
          "type": "varchar(50)",
          "primaryKey": false,
          "notNull": true
        },
        "property_name": {
          "name": "property_name",
          "type": "varchar(255)",
          "primaryKey": false,
          "notNull": true
        },
        "property_address": {
          "name": "property_address",
          "type": "text",
          "primaryKey": false,
          "notNull": false
        },
        "address_lat": {
          "name": "address_lat",
          "type": "varchar(50)",
          "primaryKey": false,
          "notNull": false
        },
        "address_lng": {
          "name": "address_lng",
          "type": "varchar(50)",
          "primaryKey": false,
          "notNull": false
        },
        "address_place_id": {
          "name": "address_place_id",
          "type": "varchar(255)",
          "primaryKey": false,
          "notNull": false
        },
        "address_formatted": {
          "name": "address_formatted",
          "type": "text",
          "primaryKey": false,
          "notNull": false
        },
        "property_type": {
          "name": "property_type",
          "type": "varchar(100)",
          "primaryKey": false,
          "notNull": false
        },
        "preferred_date": {
          "name": "preferred_date",
          "type": "varchar(50)",
          "primaryKey": false,
          "notNull": false
        },
        "preferred_time": {
          "name": "preferred_time",
          "type": "varchar(50)",
          "primaryKey": false,
          "notNull": false
        },
        "special_requirements": {
          "name": "special_requirements",
          "type": "text",
          "primaryKey": false,
          "notNull": false
        },
        "total_net_price": {
          "name": "total_net_price",
          "type": "bigint",
          "primaryKey": false,
          "notNull": true
        },
        "vat_amount": {
          "name": "vat_amount",
          "type": "bigint",
          "primaryKey": false,
          "notNull": true
        },
        "gross_amount": {
          "name": "gross_amount",
          "type": "bigint",
          "primaryKey": false,
          "notNull": true
        },
        "agb_accepted": {
          "name": "agb_accepted",
          "type": "varchar(5)",
          "primaryKey": false,
          "notNull": true,
          "default": "'false'"
        },
        "status": {
          "name": "status",
          "type": "varchar(50)",
          "primaryKey": false,
          "notNull": true,
          "default": "'pending'"
        },
        "created_at": {
          "name": "created_at",
          "type": "bigint",
          "primaryKey": false,
          "notNull": true
        },
        "confirmed_at": {
          "name": "confirmed_at",
          "type": "bigint",
          "primaryKey": false,
          "notNull": false
        }
      },
      "indexes": {},
      "foreignKeys": {
        "bookings_user_id_users_id_fk": {
          "name": "bookings_user_id_users_id_fk",
          "tableFrom": "bookings",
          "tableTo": "users",
          "columnsFrom": [
            "user_id"
          ],
          "columnsTo": [
            "id"
          ],
          "onDelete": "cascade",
          "onUpdate": "no action"
        }
      },
      "compositePrimaryKeys": {},
      "uniqueConstraints": {},
      "policies": {},
      "checkConstraints": {},
      "isRLSEnabled": false
    },
    "public.captions": {
      "name": "captions",
      "schema": "",
      "columns": {
        "id": {
          "name": "id",
          "type": "varchar",
          "primaryKey": true,
          "notNull": true
        },
        "image_id": {
          "name": "image_id",
          "type": "varchar",
          "primaryKey": false,
          "notNull": true
        },
        "caption_text": {
          "name": "caption_text",
          "type": "text",
          "primaryKey": false,
          "notNull": true
        },
        "room_type": {
          "name": "room_type",
          "type": "varchar(50)",
          "primaryKey": false,
          "notNull": false
        },
        "confidence": {
          "name": "confidence",
          "type": "bigint",
          "primaryKey": false,
          "notNull": false
        },
        "language": {
          "name": "language",
          "type": "varchar(10)",
          "primaryKey": false,
          "notNull": true,
          "default": "'de'"
        },
        "version": {
          "name": "version",
          "type": "bigint",
          "primaryKey": false,
          "notNull": true,
          "default": 1
        },
        "created_at": {
          "name": "created_at",
          "type": "bigint",
          "primaryKey": false,
          "notNull": true
        }
      },
      "indexes": {},
      "foreignKeys": {
        "captions_image_id_images_id_fk": {
          "name": "captions_image_id_images_id_fk",
          "tableFrom": "captions",
          "tableTo": "images",
          "columnsFrom": [
            "image_id"
          ],
          "columnsTo": [
            "id"
          ],
          "onDelete": "cascade",
          "onUpdate": "no action"
        }
      },
      "compositePrimaryKeys": {},
      "uniqueConstraints": {},
      "policies": {},
      "checkConstraints": {},
      "isRLSEnabled": false
    },
    "public.edited_images": {
      "name": "edited_images",
      "schema": "",
      "columns": {
        "id": {
          "name": "id",
          "type": "varchar",
          "primaryKey": true,
          "notNull": true
        },
        "shoot_id": {
          "name": "shoot_id",
          "type": "varchar",
          "primaryKey": false,
          "notNull": true
        },
        "stack_id": {
          "name": "stack_id",
          "type": "varchar",
          "primaryKey": false,
          "notNull": false
        },
        "filename": {
          "name": "filename",
          "type": "varchar(255)",
          "primaryKey": false,
          "notNull": true
        },
        "file_path": {
          "name": "file_path",
          "type": "text",
          "primaryKey": false,
          "notNull": true
        },
        "file_size": {
          "name": "file_size",
          "type": "bigint",
          "primaryKey": false,
          "notNull": false
        },
        "version": {
          "name": "version",
          "type": "bigint",
          "primaryKey": false,
          "notNull": true,
          "default": 1
        },
        "room_type": {
          "name": "room_type",
          "type": "varchar(50)",
          "primaryKey": false,
          "notNull": false
        },
        "sequence_index": {
          "name": "sequence_index",
          "type": "bigint",
          "primaryKey": false,
          "notNull": false
        },
        "client_approval_status": {
          "name": "client_approval_status",
          "type": "varchar(20)",
          "primaryKey": false,
          "notNull": true,
          "default": "'pending'"
        },
        "revision_notes": {
          "name": "revision_notes",
          "type": "text",
          "primaryKey": false,
          "notNull": false
        },
        "ai_caption": {
          "name": "ai_caption",
          "type": "text",
          "primaryKey": false,
          "notNull": false
        },
        "created_at": {
          "name": "created_at",
          "type": "bigint",
          "primaryKey": false,
          "notNull": true
        },
        "approved_at": {
          "name": "approved_at",
          "type": "bigint",
          "primaryKey": false,
          "notNull": false
        },
        "rejected_at": {
          "name": "rejected_at",
          "type": "bigint",
          "primaryKey": false,
          "notNull": false
        }
      },
      "indexes": {},
      "foreignKeys": {
        "edited_images_shoot_id_shoots_id_fk": {
          "name": "edited_images_shoot_id_shoots_id_fk",
          "tableFrom": "edited_images",
          "tableTo": "shoots",
          "columnsFrom": [
            "shoot_id"
          ],
          "columnsTo": [
            "id"
          ],
          "onDelete": "cascade",
          "onUpdate": "no action"
        },
        "edited_images_stack_id_stacks_id_fk": {
          "name": "edited_images_stack_id_stacks_id_fk",
          "tableFrom": "edited_images",
          "tableTo": "stacks",
          "columnsFrom": [
            "stack_id"
          ],
          "columnsTo": [
            "id"
          ],
          "onDelete": "set null",
          "onUpdate": "no action"
        }
      },
      "compositePrimaryKeys": {},
      "uniqueConstraints": {},
      "policies": {},
      "checkConstraints": {},
      "isRLSEnabled": false
    },
    "public.editor_tokens": {
      "name": "editor_tokens",
      "schema": "",
      "columns": {
        "id": {
          "name": "id",
          "type": "varchar",
          "primaryKey": true,
          "notNull": true
        },
        "shoot_id": {
          "name": "shoot_id",
          "type": "varchar",
          "primaryKey": false,
          "notNull": true
        },
        "token": {
          "name": "token",
          "type": "text",
          "primaryKey": false,
          "notNull": true
        },
        "token_type": {
          "name": "token_type",
          "type": "varchar(20)",
          "primaryKey": false,
          "notNull": true
        },
        "file_path": {
          "name": "file_path",
          "type": "text",
          "primaryKey": false,
          "notNull": false
        },
        "expires_at": {
          "name": "expires_at",
          "type": "bigint",
          "primaryKey": false,
          "notNull": true
        },
        "created_at": {
          "name": "created_at",
          "type": "bigint",
          "primaryKey": false,
          "notNull": true
        },
        "used_at": {
          "name": "used_at",
          "type": "bigint",
          "primaryKey": false,
          "notNull": false
        }
      },
      "indexes": {},
      "foreignKeys": {
        "editor_tokens_shoot_id_shoots_id_fk": {
          "name": "editor_tokens_shoot_id_shoots_id_fk",
          "tableFrom": "editor_tokens",
          "tableTo": "shoots",
          "columnsFrom": [
            "shoot_id"
          ],
          "columnsTo": [
            "id"
          ],
          "onDelete": "cascade",
          "onUpdate": "no action"
        }
      },
      "compositePrimaryKeys": {},
      "uniqueConstraints": {
        "editor_tokens_token_unique": {
          "name": "editor_tokens_token_unique",
          "nullsNotDistinct": false,
          "columns": [
            "token"
          ]
        }
      },
      "policies": {},
      "checkConstraints": {},
      "isRLSEnabled": false
    },
    "public.editorial_comments": {
      "name": "editorial_comments",
      "schema": "",
      "columns": {
        "id": {
          "name": "id",
          "type": "varchar",
          "primaryKey": true,
          "notNull": true
        },
        "item_id": {
          "name": "item_id",
          "type": "varchar",
          "primaryKey": false,
          "notNull": true
        },
        "user_id": {
          "name": "user_id",
          "type": "varchar",
          "primaryKey": false,
          "notNull": true
        },
        "comment": {
          "name": "comment",
          "type": "text",
          "primaryKey": false,
          "notNull": true
        },
        "created_at": {
          "name": "created_at",
          "type": "bigint",
          "primaryKey": false,
          "notNull": true
        }
      },
      "indexes": {},
      "foreignKeys": {
        "editorial_comments_item_id_editorial_items_id_fk": {
          "name": "editorial_comments_item_id_editorial_items_id_fk",
          "tableFrom": "editorial_comments",
          "tableTo": "editorial_items",
          "columnsFrom": [
            "item_id"
          ],
          "columnsTo": [
            "id"
          ],
          "onDelete": "cascade",
          "onUpdate": "no action"
        },
        "editorial_comments_user_id_users_id_fk": {
          "name": "editorial_comments_user_id_users_id_fk",
          "tableFrom": "editorial_comments",
          "tableTo": "users",
          "columnsFrom": [
            "user_id"
          ],
          "columnsTo": [
            "id"
          ],
          "onDelete": "cascade",
          "onUpdate": "no action"
        }
      },
      "compositePrimaryKeys": {},
      "uniqueConstraints": {},
      "policies": {},
      "checkConstraints": {},
      "isRLSEnabled": false
    },
    "public.editorial_items": {
      "name": "editorial_items",
      "schema": "",
      "columns": {
        "id": {
          "name": "id",
          "type": "varchar",
          "primaryKey": true,
          "notNull": true
        },
        "title": {
          "name": "title",
          "type": "varchar(255)",
          "primaryKey": false,
          "notNull": true
        },
        "type": {
          "name": "type",
          "type": "varchar(50)",
          "primaryKey": false,
          "notNull": true
        },
        "category": {
          "name": "category",
          "type": "varchar(50)",
          "primaryKey": false,
          "notNull": true
        },
        "status": {
          "name": "status",
          "type": "varchar(50)",
          "primaryKey": false,
          "notNull": true,
          "default": "'idea'"
        },
        "priority": {
          "name": "priority",
          "type": "varchar(20)",
          "primaryKey": false,
          "notNull": true,
          "default": "'normal'"
        },
        "description": {
          "name": "description",
          "type": "text",
          "primaryKey": false,
          "notNull": false
        },
        "due_date": {
          "name": "due_date",
          "type": "bigint",
          "primaryKey": false,
          "notNull": false
        },
        "publish_week": {
          "name": "publish_week",
          "type": "varchar(10)",
          "primaryKey": false,
          "notNull": false
        },
        "assignee_id": {
          "name": "assignee_id",
          "type": "varchar",
          "primaryKey": false,
          "notNull": false
        },
        "tags": {
          "name": "tags",
          "type": "text[]",
          "primaryKey": false,
          "notNull": false
        },
        "created_by": {
          "name": "created_by",
          "type": "varchar",
          "primaryKey": false,
          "notNull": true
        },
        "created_at": {
          "name": "created_at",
          "type": "bigint",
          "primaryKey": false,
          "notNull": true
        },
        "updated_at": {
          "name": "updated_at",
          "type": "bigint",
          "primaryKey": false,
          "notNull": true
        },
        "completed_at": {
          "name": "completed_at",
          "type": "bigint",
          "primaryKey": false,
          "notNull": false
        }
      },
      "indexes": {},
      "foreignKeys": {
        "editorial_items_assignee_id_users_id_fk": {
          "name": "editorial_items_assignee_id_users_id_fk",
          "tableFrom": "editorial_items",
          "tableTo": "users",
          "columnsFrom": [
            "assignee_id"
          ],
          "columnsTo": [
            "id"
          ],
          "onDelete": "set null",
          "onUpdate": "no action"
        },
        "editorial_items_created_by_users_id_fk": {
          "name": "editorial_items_created_by_users_id_fk",
          "tableFrom": "editorial_items",
          "tableTo": "users",
          "columnsFrom": [
            "created_by"
          ],
          "columnsTo": [
            "id"
          ],
          "onDelete": "cascade",
          "onUpdate": "no action"
        }
      },
      "compositePrimaryKeys": {},
      "uniqueConstraints": {},
      "policies": {},
      "checkConstraints": {},
      "isRLSEnabled": false
    },
    "public.exposes": {
      "name": "exposes",
      "schema": "",
      "columns": {
        "id": {
          "name": "id",
          "type": "varchar",
          "primaryKey": true,
          "notNull": true
        },
        "job_id": {
          "name": "job_id",
          "type": "varchar",
          "primaryKey": false,
          "notNull": true
        },
        "summary": {
          "name": "summary",
          "type": "text",
          "primaryKey": false,
          "notNull": true
        },
        "highlights": {
          "name": "highlights",
          "type": "text",
          "primaryKey": false,
          "notNull": false
        },
        "neighborhood": {
          "name": "neighborhood",
          "type": "text",
          "primaryKey": false,
          "notNull": false
        },
        "tech_details": {
          "name": "tech_details",
          "type": "text",
          "primaryKey": false,
          "notNull": false
        },
        "word_count": {
          "name": "word_count",
          "type": "bigint",
          "primaryKey": false,
          "notNull": false
        },
        "version": {
          "name": "version",
          "type": "bigint",
          "primaryKey": false,
          "notNull": true,
          "default": 1
        },
        "created_at": {
          "name": "created_at",
          "type": "bigint",
          "primaryKey": false,
          "notNull": true
        }
      },
      "indexes": {},
      "foreignKeys": {
        "exposes_job_id_jobs_id_fk": {
          "name": "exposes_job_id_jobs_id_fk",
          "tableFrom": "exposes",
          "tableTo": "jobs",
          "columnsFrom": [
            "job_id"
          ],
          "columnsTo": [
            "id"
          ],
          "onDelete": "cascade",
          "onUpdate": "no action"
        }
      },
      "compositePrimaryKeys": {},
      "uniqueConstraints": {},
      "policies": {},
      "checkConstraints": {},
      "isRLSEnabled": false
    },
    "public.galleries": {
      "name": "galleries",
      "schema": "",
      "columns": {
        "id": {
          "name": "id",
          "type": "varchar",
          "primaryKey": true,
          "notNull": true
        },
        "gallery_type": {
          "name": "gallery_type",
          "type": "varchar(50)",
          "primaryKey": false,
          "notNull": true
        },
        "user_id": {
          "name": "user_id",
          "type": "varchar",
          "primaryKey": false,
          "notNull": true
        },
        "shoot_id": {
          "name": "shoot_id",
          "type": "varchar",
          "primaryKey": false,
          "notNull": false
        },
        "job_id": {
          "name": "job_id",
          "type": "varchar",
          "primaryKey": false,
          "notNull": false
        },
        "title": {
          "name": "title",
          "type": "varchar(255)",
          "primaryKey": false,
          "notNull": true
        },
        "description": {
          "name": "description",
          "type": "text",
          "primaryKey": false,
          "notNull": false
        },
        "status": {
          "name": "status",
          "type": "varchar(50)",
          "primaryKey": false,
          "notNull": true,
          "default": "'uploaded'"
        },
        "global_style_preset": {
          "name": "global_style_preset",
          "type": "varchar(50)",
          "primaryKey": false,
          "notNull": false
        },
        "global_window_preset": {
          "name": "global_window_preset",
          "type": "varchar(50)",
          "primaryKey": false,
          "notNull": false
        },
        "global_sky_preset": {
          "name": "global_sky_preset",
          "type": "varchar(100)",
          "primaryKey": false,
          "notNull": false
        },
        "global_fireplace": {
          "name": "global_fireplace",
          "type": "varchar(5)",
          "primaryKey": false,
          "notNull": true,
          "default": "'false'"
        },
        "global_retouch": {
          "name": "global_retouch",
          "type": "varchar(5)",
          "primaryKey": false,
          "notNull": true,
          "default": "'true'"
        },
        "global_enhancements": {
          "name": "global_enhancements",
          "type": "varchar(5)",
          "primaryKey": false,
          "notNull": true,
          "default": "'true'"
        },
        "finalized_at": {
          "name": "finalized_at",
          "type": "bigint",
          "primaryKey": false,
          "notNull": false
        },
        "created_at": {
          "name": "created_at",
          "type": "bigint",
          "primaryKey": false,
          "notNull": true
        },
        "updated_at": {
          "name": "updated_at",
          "type": "bigint",
          "primaryKey": false,
          "notNull": true
        }
      },
      "indexes": {},
      "foreignKeys": {
        "galleries_user_id_users_id_fk": {
          "name": "galleries_user_id_users_id_fk",
          "tableFrom": "galleries",
          "tableTo": "users",
          "columnsFrom": [
            "user_id"
          ],
          "columnsTo": [
            "id"
          ],
          "onDelete": "cascade",
          "onUpdate": "no action"
        },
        "galleries_shoot_id_shoots_id_fk": {
          "name": "galleries_shoot_id_shoots_id_fk",
          "tableFrom": "galleries",
          "tableTo": "shoots",
          "columnsFrom": [
            "shoot_id"
          ],
          "columnsTo": [
            "id"
          ],
          "onDelete": "set null",
          "onUpdate": "no action"
        },
        "galleries_job_id_jobs_id_fk": {
          "name": "galleries_job_id_jobs_id_fk",
          "tableFrom": "galleries",
          "tableTo": "jobs",
          "columnsFrom": [
            "job_id"
          ],
          "columnsTo": [
            "id"
          ],
          "onDelete": "set null",
          "onUpdate": "no action"
        }
      },
      "compositePrimaryKeys": {},
      "uniqueConstraints": {},
      "policies": {},
      "checkConstraints": {},
      "isRLSEnabled": false
    },
    "public.gallery_annotations": {
      "name": "gallery_annotations",
      "schema": "",
      "columns": {
        "id": {
          "name": "id",
          "type": "varchar",
          "primaryKey": true,
          "notNull": true
        },
        "file_id": {
          "name": "file_id",
          "type": "varchar",
          "primaryKey": false,
          "notNull": true
        },
        "user_id": {
          "name": "user_id",
          "type": "varchar",
          "primaryKey": false,
          "notNull": true
        },
        "annotation_type": {
          "name": "annotation_type",
          "type": "varchar(50)",
          "primaryKey": false,
          "notNull": true
        },
        "comment": {
          "name": "comment",
          "type": "text",
          "primaryKey": false,
          "notNull": false
        },
        "mask_path": {
          "name": "mask_path",
          "type": "text",
          "primaryKey": false,
          "notNull": false
        },
        "created_at": {
          "name": "created_at",
          "type": "bigint",
          "primaryKey": false,
          "notNull": true
        }
      },
      "indexes": {},
      "foreignKeys": {
        "gallery_annotations_file_id_gallery_files_id_fk": {
          "name": "gallery_annotations_file_id_gallery_files_id_fk",
          "tableFrom": "gallery_annotations",
          "tableTo": "gallery_files",
          "columnsFrom": [
            "file_id"
          ],
          "columnsTo": [
            "id"
          ],
          "onDelete": "cascade",
          "onUpdate": "no action"
        },
        "gallery_annotations_user_id_users_id_fk": {
          "name": "gallery_annotations_user_id_users_id_fk",
          "tableFrom": "gallery_annotations",
          "tableTo": "users",
          "columnsFrom": [
            "user_id"
          ],
          "columnsTo": [
            "id"
          ],
          "onDelete": "cascade",
          "onUpdate": "no action"
        }
      },
      "compositePrimaryKeys": {},
      "uniqueConstraints": {},
      "policies": {},
      "checkConstraints": {},
      "isRLSEnabled": false
    },
    "public.gallery_files": {
      "name": "gallery_files",
      "schema": "",
      "columns": {
        "id": {
          "name": "id",
          "type": "varchar",
          "primaryKey": true,
          "notNull": true
        },
        "gallery_id": {
          "name": "gallery_id",
          "type": "varchar",
          "primaryKey": false,
          "notNull": true
        },
        "original_filename": {
          "name": "original_filename",
          "type": "varchar(255)",
          "primaryKey": false,
          "notNull": true
        },
        "stored_filename": {
          "name": "stored_filename",
          "type": "varchar(255)",
          "primaryKey": false,
          "notNull": true
        },
        "file_path": {
          "name": "file_path",
          "type": "text",
          "primaryKey": false,
          "notNull": true
        },
        "thumbnail_path": {
          "name": "thumbnail_path",
          "type": "text",
          "primaryKey": false,
          "notNull": false
        },
        "file_type": {
          "name": "file_type",
          "type": "varchar(50)",
          "primaryKey": false,
          "notNull": true
        },
        "file_size": {
          "name": "file_size",
          "type": "bigint",
          "primaryKey": false,
          "notNull": false
        },
        "room_type": {
          "name": "room_type",
          "type": "varchar(50)",
          "primaryKey": false,
          "notNull": false
        },
        "sequence_index": {
          "name": "sequence_index",
          "type": "bigint",
          "primaryKey": false,
          "notNull": true
        },
        "style_preset": {
          "name": "style_preset",
          "type": "varchar(50)",
          "primaryKey": false,
          "notNull": false
        },
        "window_preset": {
          "name": "window_preset",
          "type": "varchar(50)",
          "primaryKey": false,
          "notNull": false
        },
        "sky_preset": {
          "name": "sky_preset",
          "type": "varchar(100)",
          "primaryKey": false,
          "notNull": false
        },
        "fireplace_enabled": {
          "name": "fireplace_enabled",
          "type": "varchar(5)",
          "primaryKey": false,
          "notNull": false
        },
        "retouch_enabled": {
          "name": "retouch_enabled",
          "type": "varchar(5)",
          "primaryKey": false,
          "notNull": false
        },
        "enhancements_enabled": {
          "name": "enhancements_enabled",
          "type": "varchar(5)",
          "primaryKey": false,
          "notNull": false
        },
        "status": {
          "name": "status",
          "type": "varchar(50)",
          "primaryKey": false,
          "notNull": true,
          "default": "'uploaded'"
        },
        "created_at": {
          "name": "created_at",
          "type": "bigint",
          "primaryKey": false,
          "notNull": true
        },
        "updated_at": {
          "name": "updated_at",
          "type": "bigint",
          "primaryKey": false,
          "notNull": true
        }
      },
      "indexes": {},
      "foreignKeys": {
        "gallery_files_gallery_id_galleries_id_fk": {
          "name": "gallery_files_gallery_id_galleries_id_fk",
          "tableFrom": "gallery_files",
          "tableTo": "galleries",
          "columnsFrom": [
            "gallery_id"
          ],
          "columnsTo": [
            "id"
          ],
          "onDelete": "cascade",
          "onUpdate": "no action"
        }
      },
      "compositePrimaryKeys": {},
      "uniqueConstraints": {},
      "policies": {},
      "checkConstraints": {},
      "isRLSEnabled": false
    },
    "public.image_comments": {
      "name": "image_comments",
      "schema": "",
      "columns": {
        "id": {
          "name": "id",
          "type": "varchar",
          "primaryKey": true,
          "notNull": true
        },
        "user_id": {
          "name": "user_id",
          "type": "varchar",
          "primaryKey": false,
          "notNull": true
        },
        "image_id": {
          "name": "image_id",
          "type": "varchar",
          "primaryKey": false,
          "notNull": true
        },
        "comment": {
          "name": "comment",
          "type": "text",
          "primaryKey": false,
          "notNull": true
        },
        "alt_text": {
          "name": "alt_text",
          "type": "text",
          "primaryKey": false,
          "notNull": false
        },
        "created_at": {
          "name": "created_at",
          "type": "bigint",
          "primaryKey": false,
          "notNull": true
        }
      },
      "indexes": {},
      "foreignKeys": {
        "image_comments_user_id_users_id_fk": {
          "name": "image_comments_user_id_users_id_fk",
          "tableFrom": "image_comments",
          "tableTo": "users",
          "columnsFrom": [
            "user_id"
          ],
          "columnsTo": [
            "id"
          ],
          "onDelete": "cascade",
          "onUpdate": "no action"
        },
        "image_comments_image_id_edited_images_id_fk": {
          "name": "image_comments_image_id_edited_images_id_fk",
          "tableFrom": "image_comments",
          "tableTo": "edited_images",
          "columnsFrom": [
            "image_id"
          ],
          "columnsTo": [
            "id"
          ],
          "onDelete": "cascade",
          "onUpdate": "no action"
        }
      },
      "compositePrimaryKeys": {},
      "uniqueConstraints": {},
      "policies": {},
      "checkConstraints": {},
      "isRLSEnabled": false
    },
    "public.image_favorites": {
      "name": "image_favorites",
      "schema": "",
      "columns": {
        "id": {
          "name": "id",
          "type": "varchar",
          "primaryKey": true,
          "notNull": true
        },
        "user_id": {
          "name": "user_id",
          "type": "varchar",
          "primaryKey": false,
          "notNull": true
        },
        "image_id": {
          "name": "image_id",
          "type": "varchar",
          "primaryKey": false,
          "notNull": true
        },
        "created_at": {
          "name": "created_at",
          "type": "bigint",
          "primaryKey": false,
          "notNull": true
        }
      },
      "indexes": {},
      "foreignKeys": {
        "image_favorites_user_id_users_id_fk": {
          "name": "image_favorites_user_id_users_id_fk",
          "tableFrom": "image_favorites",
          "tableTo": "users",
          "columnsFrom": [
            "user_id"
          ],
          "columnsTo": [
            "id"
          ],
          "onDelete": "cascade",
          "onUpdate": "no action"
        },
        "image_favorites_image_id_edited_images_id_fk": {
          "name": "image_favorites_image_id_edited_images_id_fk",
          "tableFrom": "image_favorites",
          "tableTo": "edited_images",
          "columnsFrom": [
            "image_id"
          ],
          "columnsTo": [
            "id"
          ],
          "onDelete": "cascade",
          "onUpdate": "no action"
        }
      },
      "compositePrimaryKeys": {},
      "uniqueConstraints": {},
      "policies": {},
      "checkConstraints": {},
      "isRLSEnabled": false
    },
    "public.images": {
      "name": "images",
      "schema": "",
      "columns": {
        "id": {
          "name": "id",
          "type": "varchar",
          "primaryKey": true,
          "notNull": true
        },
        "shoot_id": {
          "name": "shoot_id",
          "type": "varchar",
          "primaryKey": false,
          "notNull": true
        },
        "stack_id": {
          "name": "stack_id",
          "type": "varchar",
          "primaryKey": false,
          "notNull": false
        },
        "original_filename": {
          "name": "original_filename",
          "type": "varchar(255)",
          "primaryKey": false,
          "notNull": true
        },
        "renamed_filename": {
          "name": "renamed_filename",
          "type": "varchar(255)",
          "primaryKey": false,
          "notNull": false
        },
        "file_path": {
          "name": "file_path",
          "type": "text",
          "primaryKey": false,
          "notNull": true
        },
        "preview_path": {
          "name": "preview_path",
          "type": "text",
          "primaryKey": false,
          "notNull": false
        },
        "file_size": {
          "name": "file_size",
          "type": "bigint",
          "primaryKey": false,
          "notNull": false
        },
        "mime_type": {
          "name": "mime_type",
          "type": "varchar(100)",
          "primaryKey": false,
          "notNull": false
        },
        "exif_date": {
          "name": "exif_date",
          "type": "bigint",
          "primaryKey": false,
          "notNull": false
        },
        "exposure_value": {
          "name": "exposure_value",
          "type": "varchar(10)",
          "primaryKey": false,
          "notNull": false
        },
        "position_in_stack": {
          "name": "position_in_stack",
          "type": "bigint",
          "primaryKey": false,
          "notNull": false
        },
        "room_type": {
          "name": "room_type",
          "type": "varchar(50)",
          "primaryKey": false,
          "notNull": false
        },
        "filename_pattern_version": {
          "name": "filename_pattern_version",
          "type": "varchar(10)",
          "primaryKey": false,
          "notNull": false,
          "default": "'v3.1'"
        },
        "validated_at": {
          "name": "validated_at",
          "type": "bigint",
          "primaryKey": false,
          "notNull": false
        },
        "classified_at": {
          "name": "classified_at",
          "type": "bigint",
          "primaryKey": false,
          "notNull": false
        },
        "created_at": {
          "name": "created_at",
          "type": "bigint",
          "primaryKey": false,
          "notNull": true
        }
      },
      "indexes": {},
      "foreignKeys": {
        "images_shoot_id_shoots_id_fk": {
          "name": "images_shoot_id_shoots_id_fk",
          "tableFrom": "images",
          "tableTo": "shoots",
          "columnsFrom": [
            "shoot_id"
          ],
          "columnsTo": [
            "id"
          ],
          "onDelete": "cascade",
          "onUpdate": "no action"
        },
        "images_stack_id_stacks_id_fk": {
          "name": "images_stack_id_stacks_id_fk",
          "tableFrom": "images",
          "tableTo": "stacks",
          "columnsFrom": [
            "stack_id"
          ],
          "columnsTo": [
            "id"
          ],
          "onDelete": "set null",
          "onUpdate": "no action"
        }
      },
      "compositePrimaryKeys": {},
      "uniqueConstraints": {},
      "policies": {},
      "checkConstraints": {},
      "isRLSEnabled": false
    },
    "public.jobs": {
      "name": "jobs",
      "schema": "",
      "columns": {
        "id": {
          "name": "id",
          "type": "varchar",
          "primaryKey": true,
          "notNull": true
        },
        "local_id": {
          "name": "local_id",
          "type": "varchar(50)",
          "primaryKey": false,
          "notNull": false
        },
        "job_number": {
          "name": "job_number",
          "type": "varchar(50)",
          "primaryKey": false,
          "notNull": true
        },
        "user_id": {
          "name": "user_id",
          "type": "varchar",
          "primaryKey": false,
          "notNull": true
        },
        "customer_name": {
          "name": "customer_name",
          "type": "varchar(255)",
          "primaryKey": false,
          "notNull": false
        },
        "property_name": {
          "name": "property_name",
          "type": "varchar(255)",
          "primaryKey": false,
          "notNull": true
        },
        "property_address": {
          "name": "property_address",
          "type": "text",
          "primaryKey": false,
          "notNull": false
        },
        "address_lat": {
          "name": "address_lat",
          "type": "varchar(50)",
          "primaryKey": false,
          "notNull": false
        },
        "address_lng": {
          "name": "address_lng",
          "type": "varchar(50)",
          "primaryKey": false,
          "notNull": false
        },
        "address_place_id": {
          "name": "address_place_id",
          "type": "varchar(255)",
          "primaryKey": false,
          "notNull": false
        },
        "address_formatted": {
          "name": "address_formatted",
          "type": "text",
          "primaryKey": false,
          "notNull": false
        },
        "status": {
          "name": "status",
          "type": "varchar(50)",
          "primaryKey": false,
          "notNull": true,
          "default": "'created'"
        },
        "deadline_at": {
          "name": "deadline_at",
          "type": "bigint",
          "primaryKey": false,
          "notNull": false
        },
        "deliver_gallery": {
          "name": "deliver_gallery",
          "type": "varchar(10)",
          "primaryKey": false,
          "notNull": true,
          "default": "'true'"
        },
        "deliver_alttext": {
          "name": "deliver_alttext",
          "type": "varchar(10)",
          "primaryKey": false,
          "notNull": true,
          "default": "'true'"
        },
        "deliver_expose": {
          "name": "deliver_expose",
          "type": "varchar(10)",
          "primaryKey": false,
          "notNull": true,
          "default": "'false'"
        },
        "selected_user_id": {
          "name": "selected_user_id",
          "type": "varchar(50)",
          "primaryKey": false,
          "notNull": false
        },
        "selected_user_initials": {
          "name": "selected_user_initials",
          "type": "varchar(10)",
          "primaryKey": false,
          "notNull": false
        },
        "selected_user_code": {
          "name": "selected_user_code",
          "type": "varchar(20)",
          "primaryKey": false,
          "notNull": false
        },
        "created_at": {
          "name": "created_at",
          "type": "bigint",
          "primaryKey": false,
          "notNull": true
        }
      },
      "indexes": {},
      "foreignKeys": {
        "jobs_user_id_users_id_fk": {
          "name": "jobs_user_id_users_id_fk",
          "tableFrom": "jobs",
          "tableTo": "users",
          "columnsFrom": [
            "user_id"
          ],
          "columnsTo": [
            "id"
          ],
          "onDelete": "cascade",
          "onUpdate": "no action"
        }
      },
      "compositePrimaryKeys": {},
      "uniqueConstraints": {
        "jobs_local_id_unique": {
          "name": "jobs_local_id_unique",
          "nullsNotDistinct": false,
          "columns": [
            "local_id"
          ]
        },
        "jobs_job_number_unique": {
          "name": "jobs_job_number_unique",
          "nullsNotDistinct": false,
          "columns": [
            "job_number"
          ]
        }
      },
      "policies": {},
      "checkConstraints": {},
      "isRLSEnabled": false
    },
    "public.orders": {
      "name": "orders",
      "schema": "",
      "columns": {
        "id": {
          "name": "id",
          "type": "varchar",
          "primaryKey": true,
          "notNull": true
        },
        "user_id": {
          "name": "user_id",
          "type": "varchar",
          "primaryKey": false,
          "notNull": true
        },
        "property_name": {
          "name": "property_name",
          "type": "varchar(255)",
          "primaryKey": false,
          "notNull": true
        },
        "contact_name": {
          "name": "contact_name",
          "type": "varchar(255)",
          "primaryKey": false,
          "notNull": true
        },
        "contact_email": {
          "name": "contact_email",
          "type": "varchar(255)",
          "primaryKey": false,
          "notNull": true
        },
        "contact_phone": {
          "name": "contact_phone",
          "type": "varchar(50)",
          "primaryKey": false,
          "notNull": false
        },
        "property_address": {
          "name": "property_address",
          "type": "text",
          "primaryKey": false,
          "notNull": true
        },
        "address_lat": {
          "name": "address_lat",
          "type": "varchar(50)",
          "primaryKey": false,
          "notNull": false
        },
        "address_lng": {
          "name": "address_lng",
          "type": "varchar(50)",
          "primaryKey": false,
          "notNull": false
        },
        "address_place_id": {
          "name": "address_place_id",
          "type": "varchar(255)",
          "primaryKey": false,
          "notNull": false
        },
        "address_formatted": {
          "name": "address_formatted",
          "type": "text",
          "primaryKey": false,
          "notNull": false
        },
        "address_location_type": {
          "name": "address_location_type",
          "type": "varchar(50)",
          "primaryKey": false,
          "notNull": false
        },
        "preferred_date": {
          "name": "preferred_date",
          "type": "varchar(50)",
          "primaryKey": false,
          "notNull": false
        },
        "notes": {
          "name": "notes",
          "type": "text",
          "primaryKey": false,
          "notNull": false
        },
        "status": {
          "name": "status",
          "type": "varchar(50)",
          "primaryKey": false,
          "notNull": true,
          "default": "'pending'"
        },
        "created_at": {
          "name": "created_at",
          "type": "bigint",
          "primaryKey": false,
          "notNull": true
        }
      },
      "indexes": {},
      "foreignKeys": {
        "orders_user_id_users_id_fk": {
          "name": "orders_user_id_users_id_fk",
          "tableFrom": "orders",
          "tableTo": "users",
          "columnsFrom": [
            "user_id"
          ],
          "columnsTo": [
            "id"
          ],
          "onDelete": "cascade",
          "onUpdate": "no action"
        }
      },
      "compositePrimaryKeys": {},
      "uniqueConstraints": {},
      "policies": {},
      "checkConstraints": {},
      "isRLSEnabled": false
    },
    "public.password_reset_tokens": {
      "name": "password_reset_tokens",
      "schema": "",
      "columns": {
        "id": {
          "name": "id",
          "type": "varchar",
          "primaryKey": true,
          "notNull": true
        },
        "user_id": {
          "name": "user_id",
          "type": "varchar",
          "primaryKey": false,
          "notNull": true
        },
        "token": {
          "name": "token",
          "type": "text",
          "primaryKey": false,
          "notNull": true
        },
        "expires_at": {
          "name": "expires_at",
          "type": "bigint",
          "primaryKey": false,
          "notNull": true
        },
        "created_at": {
          "name": "created_at",
          "type": "bigint",
          "primaryKey": false,
          "notNull": true
        }
      },
      "indexes": {},
      "foreignKeys": {
        "password_reset_tokens_user_id_users_id_fk": {
          "name": "password_reset_tokens_user_id_users_id_fk",
          "tableFrom": "password_reset_tokens",
          "tableTo": "users",
          "columnsFrom": [
            "user_id"
          ],
          "columnsTo": [
            "id"
          ],
          "onDelete": "cascade",
          "onUpdate": "no action"
        }
      },
      "compositePrimaryKeys": {},
      "uniqueConstraints": {
        "password_reset_tokens_token_unique": {
          "name": "password_reset_tokens_token_unique",
          "nullsNotDistinct": false,
          "columns": [
            "token"
          ]
        }
      },
      "policies": {},
      "checkConstraints": {},
      "isRLSEnabled": false
    },
    "public.personal_access_tokens": {
      "name": "personal_access_tokens",
      "schema": "",
      "columns": {
        "id": {
          "name": "id",
          "type": "varchar",
          "primaryKey": true,
          "notNull": true
        },
        "user_id": {
          "name": "user_id",
          "type": "varchar",
          "primaryKey": false,
          "notNull": true
        },
        "token": {
          "name": "token",
          "type": "text",
          "primaryKey": false,
          "notNull": true
        },
        "name": {
          "name": "name",
          "type": "varchar(100)",
          "primaryKey": false,
          "notNull": false
        },
        "scopes": {
          "name": "scopes",
          "type": "text",
          "primaryKey": false,
          "notNull": true
        },
        "expires_at": {
          "name": "expires_at",
          "type": "bigint",
          "primaryKey": false,
          "notNull": true
        },
        "last_used_at": {
          "name": "last_used_at",
          "type": "bigint",
          "primaryKey": false,
          "notNull": false
        },
        "last_used_ip": {
          "name": "last_used_ip",
          "type": "varchar(45)",
          "primaryKey": false,
          "notNull": false
        },
        "created_at": {
          "name": "created_at",
          "type": "bigint",
          "primaryKey": false,
          "notNull": true
        },
        "revoked_at": {
          "name": "revoked_at",
          "type": "bigint",
          "primaryKey": false,
          "notNull": false
        }
      },
      "indexes": {},
      "foreignKeys": {
        "personal_access_tokens_user_id_users_id_fk": {
          "name": "personal_access_tokens_user_id_users_id_fk",
          "tableFrom": "personal_access_tokens",
          "tableTo": "users",
          "columnsFrom": [
            "user_id"
          ],
          "columnsTo": [
            "id"
          ],
          "onDelete": "cascade",
          "onUpdate": "no action"
        }
      },
      "compositePrimaryKeys": {},
      "uniqueConstraints": {
        "personal_access_tokens_token_unique": {
          "name": "personal_access_tokens_token_unique",
          "nullsNotDistinct": false,
          "columns": [
            "token"
          ]
        }
      },
      "policies": {},
      "checkConstraints": {},
      "isRLSEnabled": false
    },
    "public.refresh_tokens": {
      "name": "refresh_tokens",
      "schema": "",
      "columns": {
        "id": {
          "name": "id",
          "type": "varchar",
          "primaryKey": true,
          "notNull": true
        },
        "user_id": {
          "name": "user_id",
          "type": "varchar",
          "primaryKey": false,
          "notNull": true
        },
        "token": {
          "name": "token",
          "type": "text",
          "primaryKey": false,
          "notNull": true
        },
        "expires_at": {
          "name": "expires_at",
          "type": "bigint",
          "primaryKey": false,
          "notNull": true
        },
        "created_at": {
          "name": "created_at",
          "type": "bigint",
          "primaryKey": false,
          "notNull": true
        }
      },
      "indexes": {},
      "foreignKeys": {
        "refresh_tokens_user_id_users_id_fk": {
          "name": "refresh_tokens_user_id_users_id_fk",
          "tableFrom": "refresh_tokens",
          "tableTo": "users",
          "columnsFrom": [
            "user_id"
          ],
          "columnsTo": [
            "id"
          ],
          "onDelete": "cascade",
          "onUpdate": "no action"
        }
      },
      "compositePrimaryKeys": {},
      "uniqueConstraints": {
        "refresh_tokens_token_unique": {
          "name": "refresh_tokens_token_unique",
          "nullsNotDistinct": false,
          "columns": [
            "token"
          ]
        }
      },
      "policies": {},
      "checkConstraints": {},
      "isRLSEnabled": false
    },
    "public.seo_metadata": {
      "name": "seo_metadata",
      "schema": "",
      "columns": {
        "id": {
          "name": "id",
          "type": "varchar",
          "primaryKey": true,
          "notNull": true
        },
        "page_path": {
          "name": "page_path",
          "type": "varchar(255)",
          "primaryKey": false,
          "notNull": true
        },
        "page_title": {
          "name": "page_title",
          "type": "varchar(255)",
          "primaryKey": false,
          "notNull": true
        },
        "meta_description": {
          "name": "meta_description",
          "type": "text",
          "primaryKey": false,
          "notNull": true
        },
        "og_image": {
          "name": "og_image",
          "type": "varchar(500)",
          "primaryKey": false,
          "notNull": false
        },
        "alt_text": {
          "name": "alt_text",
          "type": "text",
          "primaryKey": false,
          "notNull": false
        },
        "updated_at": {
          "name": "updated_at",
          "type": "bigint",
          "primaryKey": false,
          "notNull": true
        },
        "updated_by": {
          "name": "updated_by",
          "type": "varchar",
          "primaryKey": false,
          "notNull": false
        }
      },
      "indexes": {},
      "foreignKeys": {
        "seo_metadata_updated_by_users_id_fk": {
          "name": "seo_metadata_updated_by_users_id_fk",
          "tableFrom": "seo_metadata",
          "tableTo": "users",
          "columnsFrom": [
            "updated_by"
          ],
          "columnsTo": [
            "id"
          ],
          "onDelete": "set null",
          "onUpdate": "no action"
        }
      },
      "compositePrimaryKeys": {},
      "uniqueConstraints": {
        "seo_metadata_page_path_unique": {
          "name": "seo_metadata_page_path_unique",
          "nullsNotDistinct": false,
          "columns": [
            "page_path"
          ]
        }
      },
      "policies": {},
      "checkConstraints": {},
      "isRLSEnabled": false
    },
    "public.services": {
      "name": "services",
      "schema": "",
      "columns": {
        "id": {
          "name": "id",
          "type": "varchar",
          "primaryKey": true,
          "notNull": true
        },
        "service_code": {
          "name": "service_code",
          "type": "varchar(10)",
          "primaryKey": false,
          "notNull": true
        },
        "category": {
          "name": "category",
          "type": "varchar(50)",
          "primaryKey": false,
          "notNull": true
        },
        "name": {
          "name": "name",
          "type": "varchar(255)",
          "primaryKey": false,
          "notNull": true
        },
        "description": {
          "name": "description",
          "type": "text",
          "primaryKey": false,
          "notNull": false
        },
        "net_price": {
          "name": "net_price",
          "type": "bigint",
          "primaryKey": false,
          "notNull": false
        },
        "price_note": {
          "name": "price_note",
          "type": "text",
          "primaryKey": false,
          "notNull": false
        },
        "notes": {
          "name": "notes",
          "type": "text",
          "primaryKey": false,
          "notNull": false
        },
        "is_active": {
          "name": "is_active",
          "type": "varchar(5)",
          "primaryKey": false,
          "notNull": true,
          "default": "'true'"
        },
        "created_at": {
          "name": "created_at",
          "type": "bigint",
          "primaryKey": false,
          "notNull": true
        }
      },
      "indexes": {},
      "foreignKeys": {},
      "compositePrimaryKeys": {},
      "uniqueConstraints": {
        "services_service_code_unique": {
          "name": "services_service_code_unique",
          "nullsNotDistinct": false,
          "columns": [
            "service_code"
          ]
        }
      },
      "policies": {},
      "checkConstraints": {},
      "isRLSEnabled": false
    },
    "public.sessions": {
      "name": "sessions",
      "schema": "",
      "columns": {
        "id": {
          "name": "id",
          "type": "varchar",
          "primaryKey": true,
          "notNull": true
        },
        "user_id": {
          "name": "user_id",
          "type": "varchar",
          "primaryKey": false,
          "notNull": true
        },
        "expires_at": {
          "name": "expires_at",
          "type": "bigint",
          "primaryKey": false,
          "notNull": true
        }
      },
      "indexes": {},
      "foreignKeys": {
        "sessions_user_id_users_id_fk": {
          "name": "sessions_user_id_users_id_fk",
          "tableFrom": "sessions",
          "tableTo": "users",
          "columnsFrom": [
            "user_id"
          ],
          "columnsTo": [
            "id"
          ],
          "onDelete": "cascade",
          "onUpdate": "no action"
        }
      },
      "compositePrimaryKeys": {},
      "uniqueConstraints": {},
      "policies": {},
      "checkConstraints": {},
      "isRLSEnabled": false
    },
    "public.shoots": {
      "name": "shoots",
      "schema": "",
      "columns": {
        "id": {
          "name": "id",
          "type": "varchar",
          "primaryKey": true,
          "notNull": true
        },
        "shoot_code": {
          "name": "shoot_code",
          "type": "varchar(5)",
          "primaryKey": false,
          "notNull": true
        },
        "job_id": {
          "name": "job_id",
          "type": "varchar",
          "primaryKey": false,
          "notNull": true
        },
        "status": {
          "name": "status",
          "type": "varchar(50)",
          "primaryKey": false,
          "notNull": true,
          "default": "'initialized'"
        },
        "created_at": {
          "name": "created_at",
          "type": "bigint",
          "primaryKey": false,
          "notNull": true
        },
        "intake_completed_at": {
          "name": "intake_completed_at",
          "type": "bigint",
          "primaryKey": false,
          "notNull": false
        },
        "handoff_generated_at": {
          "name": "handoff_generated_at",
          "type": "bigint",
          "primaryKey": false,
          "notNull": false
        },
        "editor_returned_at": {
          "name": "editor_returned_at",
          "type": "bigint",
          "primaryKey": false,
          "notNull": false
        }
      },
      "indexes": {},
      "foreignKeys": {
        "shoots_job_id_jobs_id_fk": {
          "name": "shoots_job_id_jobs_id_fk",
          "tableFrom": "shoots",
          "tableTo": "jobs",
          "columnsFrom": [
            "job_id"
          ],
          "columnsTo": [
            "id"
          ],
          "onDelete": "cascade",
          "onUpdate": "no action"
        }
      },
      "compositePrimaryKeys": {},
      "uniqueConstraints": {
        "shoots_shoot_code_unique": {
          "name": "shoots_shoot_code_unique",
          "nullsNotDistinct": false,
          "columns": [
            "shoot_code"
          ]
        }
      },
      "policies": {},
      "checkConstraints": {},
      "isRLSEnabled": false
    },
    "public.stacks": {
      "name": "stacks",
      "schema": "",
      "columns": {
        "id": {
          "name": "id",
          "type": "varchar",
          "primaryKey": true,
          "notNull": true
        },
        "shoot_id": {
          "name": "shoot_id",
          "type": "varchar",
          "primaryKey": false,
          "notNull": true
        },
        "stack_number": {
          "name": "stack_number",
          "type": "varchar(10)",
          "primaryKey": false,
          "notNull": true
        },
        "room_type": {
          "name": "room_type",
          "type": "varchar(50)",
          "primaryKey": false,
          "notNull": true,
          "default": "'undefined_space'"
        },
        "frame_count": {
          "name": "frame_count",
          "type": "bigint",
          "primaryKey": false,
          "notNull": true,
          "default": 5
        },
        "sequence_index": {
          "name": "sequence_index",
          "type": "bigint",
          "primaryKey": false,
          "notNull": true
        },
        "created_at": {
          "name": "created_at",
          "type": "bigint",
          "primaryKey": false,
          "notNull": true
        }
      },
      "indexes": {},
      "foreignKeys": {
        "stacks_shoot_id_shoots_id_fk": {
          "name": "stacks_shoot_id_shoots_id_fk",
          "tableFrom": "stacks",
          "tableTo": "shoots",
          "columnsFrom": [
            "shoot_id"
          ],
          "columnsTo": [
            "id"
          ],
          "onDelete": "cascade",
          "onUpdate": "no action"
        }
      },
      "compositePrimaryKeys": {},
      "uniqueConstraints": {},
      "policies": {},
      "checkConstraints": {},
      "isRLSEnabled": false
    },
    "public.upload_sessions": {
      "name": "upload_sessions",
      "schema": "",
      "columns": {
        "id": {
          "name": "id",
          "type": "varchar",
          "primaryKey": true,
          "notNull": true
        },
        "user_id": {
          "name": "user_id",
          "type": "varchar",
          "primaryKey": false,
          "notNull": true
        },
        "shoot_id": {
          "name": "shoot_id",
          "type": "varchar",
          "primaryKey": false,
          "notNull": true
        },
        "filename": {
          "name": "filename",
          "type": "varchar(255)",
          "primaryKey": false,
          "notNull": true
        },
        "room_type": {
          "name": "room_type",
          "type": "varchar(50)",
          "primaryKey": false,
          "notNull": true
        },
        "stack_index": {
          "name": "stack_index",
          "type": "bigint",
          "primaryKey": false,
          "notNull": true
        },
        "stack_count": {
          "name": "stack_count",
          "type": "bigint",
          "primaryKey": false,
          "notNull": true
        },
        "r2_key": {
          "name": "r2_key",
          "type": "text",
          "primaryKey": false,
          "notNull": true
        },
        "upload_id": {
          "name": "upload_id",
          "type": "text",
          "primaryKey": false,
          "notNull": true
        },
        "file_size": {
          "name": "file_size",
          "type": "bigint",
          "primaryKey": false,
          "notNull": false
        },
        "parts": {
          "name": "parts",
          "type": "text",
          "primaryKey": false,
          "notNull": false
        },
        "status": {
          "name": "status",
          "type": "varchar(20)",
          "primaryKey": false,
          "notNull": true,
          "default": "'initiated'"
        },
        "completed_at": {
          "name": "completed_at",
          "type": "bigint",
          "primaryKey": false,
          "notNull": false
        },
        "created_at": {
          "name": "created_at",
          "type": "bigint",
          "primaryKey": false,
          "notNull": true
        }
      },
      "indexes": {},
      "foreignKeys": {
        "upload_sessions_user_id_users_id_fk": {
          "name": "upload_sessions_user_id_users_id_fk",
          "tableFrom": "upload_sessions",
          "tableTo": "users",
          "columnsFrom": [
            "user_id"
          ],
          "columnsTo": [
            "id"
          ],
          "onDelete": "cascade",
          "onUpdate": "no action"
        },
        "upload_sessions_shoot_id_shoots_id_fk": {
          "name": "upload_sessions_shoot_id_shoots_id_fk",
          "tableFrom": "upload_sessions",
          "tableTo": "shoots",
          "columnsFrom": [
            "shoot_id"
          ],
          "columnsTo": [
            "id"
          ],
          "onDelete": "cascade",
          "onUpdate": "no action"
        }
      },
      "compositePrimaryKeys": {},
      "uniqueConstraints": {},
      "policies": {},
      "checkConstraints": {},
      "isRLSEnabled": false
    },
    "public.users": {
      "name": "users",
      "schema": "",
      "columns": {
        "id": {
          "name": "id",
          "type": "varchar",
          "primaryKey": true,
          "notNull": true
        },
        "email": {
          "name": "email",
          "type": "varchar(255)",
          "primaryKey": false,
          "notNull": true
        },
        "hashed_password": {
          "name": "hashed_password",
          "type": "text",
          "primaryKey": false,
          "notNull": true
        },
        "role": {
          "name": "role",
          "type": "varchar(20)",
          "primaryKey": false,
          "notNull": true,
          "default": "'client'"
        },
        "credits": {
          "name": "credits",
          "type": "bigint",
          "primaryKey": false,
          "notNull": true,
          "default": 0
        },
        "stripe_customer_id": {
          "name": "stripe_customer_id",
          "type": "varchar(255)",
          "primaryKey": false,
          "notNull": false
        },
        "created_at": {
          "name": "created_at",
          "type": "bigint",
          "primaryKey": false,
          "notNull": true
        }
      },
      "indexes": {},
      "foreignKeys": {},
      "compositePrimaryKeys": {},
      "uniqueConstraints": {
        "users_email_unique": {
          "name": "users_email_unique",
          "nullsNotDistinct": false,
          "columns": [
            "email"
          ]
        }
      },
      "policies": {},
      "checkConstraints": {},
      "isRLSEnabled": false
    }
  },
  "enums": {},
  "schemas": {},
  "sequences": {},
  "roles": {},
  "policies": {},
  "views": {},
  "_meta": {
    "columns": {},
    "schemas": {},
    "tables": {}
  }
}